logbase/__init__.py
logbase/main.py
logbase-0.0.1.dist-info/METADATA
logbase-0.0.1.dist-info/WHEEL
logbase-0.0.1.dist-info/top_level.txt
logbase-0.0.1.dist-info/RECORD
