Metadata-Version: 2.1
Name: logbase
Version: 0.0.1
Summary: Logbase Python Client
Home-page: https://logbase.ai
